pipetracker/__init__.py
pipetracker/api/__init__.py
pipetracker/api/main.py
pipetracker/api/routes/__init__.py
pipetracker/api/routes/trace.py
pipetracker/cli/__init__.py
pipetracker/cli/main.py
pipetracker/cli/command/__init__.py
pipetracker/cli/command/config.py
pipetracker/cli/command/trace.py
pipetracker/core/__init__.py
pipetracker/core/config_loader.py
pipetracker/core/log_scanner.py
pipetracker/core/pattern_matcher.py
pipetracker/core/performance.py
pipetracker/core/plugin_loader.py
pipetracker/core/security.py
pipetracker/core/trace_builder.py
pipetracker/core/utils.py
pipetracker/core/verifier.py
pipetracker/core/visualizer.py
pipetracker/plugins/__init__.py
pipetracker/plugins/base.py
pipetracker/plugins/datadog_plugin.py
pipetracker/plugins/gcs_plugin.py
pipetracker/plugins/kafka_plugin.py
pipetracker/plugins/loader.py
pipetracker/plugins/local_plugin.py
pipetracker/plugins/s3_plugin.py
pipetracker-0.1.3.dist-info/licenses/LICENSE
tests/__init__.py
tests/test_api.py
tests/test_cli.py
tests/test_core.py
tests/integration/__init__.py
tests/integration/test_datadog_plugin.py
tests/integration/test_full_trace.py
tests/integration/test_gcs_plugin.py
tests/integration/test_kafka_plugin.py
tests/integration/test_s3_plugin.py
tests/mocks/__init__.py
tests/unit/__init__.py
tests/unit/test_cli_commands.py
tests/unit/test_config_loader.py
tests/unit/test_datadog_plugin.py
tests/unit/test_gcs_plugin.py
tests/unit/test_kafka_plugin.py
tests/unit/test_loader.py
tests/unit/test_local_plugin.py
tests/unit/test_log_scanner.py
tests/unit/test_plugin_loader.py
tests/unit/test_s3_plugin.py
tests/unit/test_trace_builder.py
tests/unit/test_utils.py
tests/unit/test_verifier.py
tests/unit/test_visualizer.py
pipetracker-0.1.3.dist-info/METADATA
pipetracker-0.1.3.dist-info/WHEEL
pipetracker-0.1.3.dist-info/entry_points.txt
pipetracker-0.1.3.dist-info/top_level.txt
pipetracker-0.1.3.dist-info/RECORD
