Metadata-Version: 2.4
Name: pipetracker
Version: 0.1.3
Summary: Data flow and lineage tracer for         distributed microservice logs
Home-page: https://github.com/dare-afolabi/pipetracker
Author: Dare Afolabi
Author-email: dare.afolabi@outlook.com
Classifier: Programming Language :: Python :: 3
Classifier: License :: OSI Approved :: MIT License
Classifier: Operating System :: OS Independent
Requires-Python: >=3.9
License-File: LICENSE
Requires-Dist: typer>=0.19.2
Requires-Dist: pandas>=2.2.2
Requires-Dist: pydantic>=2.2.2
Requires-Dist: pydantic-settings>=1.0.5
Requires-Dist: fastapi<1.0.0,>=0.95.0
Requires-Dist: uvicorn>=0.29.0
Requires-Dist: networkx>=3.3
Requires-Dist: matplotlib>=3.8
Requires-Dist: plotly>=5.22.0
Requires-Dist: requests>=2.32.3
Requires-Dist: requests-mock>0.22.0
Requires-Dist: PyYAML>=6.0.1
Requires-Dist: cryptography>=42.0.8
Requires-Dist: filelock>=3.15.4
Provides-Extra: kafka
Requires-Dist: confluent-kafka>=2.12.0; extra == "kafka"
Requires-Dist: six>=1.16.0; extra == "kafka"
Provides-Extra: aws
Requires-Dist: boto3>=1.34.131; extra == "aws"
Provides-Extra: gcs
Requires-Dist: google-cloud-storage>=2.16.0; extra == "gcs"
Provides-Extra: datadog
Requires-Dist: datadog-api-client>=2.19.0; extra == "datadog"
Requires-Dist: datadog>=0.44; extra == "datadog"
Provides-Extra: dev
Requires-Dist: pytest>=8.2.2; extra == "dev"
Requires-Dist: pytest-cov>=5.0.0; extra == "dev"
Requires-Dist: pytest-mock>=3.10.0; extra == "dev"
Requires-Dist: black>=24.4.2; extra == "dev"
Requires-Dist: mypy>=1.10.1; extra == "dev"
Requires-Dist: isort>=5.13.2; extra == "dev"
Requires-Dist: coverage>=7.5.3; extra == "dev"
Requires-Dist: moto>=5.0.4; extra == "dev"
Requires-Dist: httpx>=0.28.1; extra == "dev"
Requires-Dist: loguru>=0.7.0; extra == "dev"
Dynamic: author
Dynamic: author-email
Dynamic: classifier
Dynamic: home-page
Dynamic: license-file
Dynamic: provides-extra
Dynamic: requires-dist
Dynamic: requires-python
Dynamic: summary
